__init__.py
apeboiy/__init__.py
apeboiy/example.py
apeboiy/inav_predict/_PointCloudPoseEstimation.py
apeboiy/inav_predict/__init__.py
apeboiy/inav_predict/__main__.py
apeboiy/obj/__init__.py
apeboiy/obj/_obj.py
apeboiy/ply/__init__.py
apeboiy/ply/_reader.py
apeboiy-0.0.16.dist-info/LICENSE
apeboiy-0.0.16.dist-info/METADATA
apeboiy-0.0.16.dist-info/WHEEL
apeboiy-0.0.16.dist-info/top_level.txt
apeboiy-0.0.16.dist-info/RECORD
