Metadata-Version: 2.1
Name: apeboiy
Version: 0.0.16
Summary: Shared AppleBoiy's packages.
Author-email: AppleBoiy <contact.chaipat@gmail.com>
Project-URL: Homepage, https://github.com/AppleBoiy
Keywords: appleboiy,shared,packages
Classifier: Programming Language :: Python :: 3
Classifier: License :: OSI Approved :: MIT License
Classifier: Operating System :: OS Independent
Requires-Python: >=3.8
License-File: LICENSE
Requires-Dist: requests >=2.25.1
Requires-Dist: numpy >=1.21.0
Requires-Dist: matplotlib
Requires-Dist: seaborn
Requires-Dist: plotly
Requires-Dist: kagglehub
Requires-Dist: pillow
Requires-Dist: onnxruntime
Requires-Dist: tqdm
